{
  "_meta": {
    "version": "phase-2b-v2-T7B",
    "date": "2026-06-01",
    "source_data": [
      "outputs/limits_20260529_132808.json (7 outer reach points)",
      "outputs/limits_20260529_134228.json (5 J2/J3 coupling points — v1, superseded by T7B)",
      "outputs/limits_20260529_135459.json (1 z_floor point)",
      "outputs/limits_t7b_20260601.json (9 T7B coupling points — 4 J2 with alarm+stable pair, 1 +20 stable only)"
    ],
    "provenance": "v1.5 (T7A) workspace/joint_ranges retained. Coupling polygon NOW DEPLOYED from T7B push-to-alarm probe: 4/4 alarm triggers fit the linear constraint J3 - J2 ≤ 60° exactly (see _coupling_note). J3 upper raised from observed 77.3° back to spec 105° because polygon now provides the real protection."
  },

  "workspace": {
    "annulus_inner_radius_mm": 123.83,
    "annulus_outer_radius_mm": 440.0,
    "z_min_mm": -197.05,
    "z_max_mm": 116.21,
    "j1_rear_dead_zone_deg": 40.21,
    "_provenance": {
      "annulus_inner": "calibrate_bounds v2, 20mm margin from observed min planar radius",
      "annulus_outer": "calibrate_bounds v2, clamped at spec reach 440mm. Real arm reached ρ≈436mm at outer_left45.",
      "z_min": "observed at floor_0 (J2=82.8, J3=77.3, J4=81.2), bare flange touching tabletop. Future tools: z_min_effective = z_min + tool.z_offset_mm.",
      "z_max": "observed only — not explicitly probed. Real arm can likely go higher (spec workspace ~280mm above origin).",
      "j1_rear_dead_zone": "now derived from data (was placeholder-capped at 40° in v1). 2 × (180° − max(|J1|)) = 2 × (180° − 159.9°) = 40.2°."
    }
  },

  "joint_ranges_deg": {
    "J1": [-159.9, 157.0],
    "J2": [-25.0, 82.8],
    "J3": [-25.0, 105.0],
    "J4": [-180.0, 180.0],
    "_provenance": {
      "note": "v2 calibrator applies spec-fallback automatically for un-probed sides. J3 upper is now spec 105° because the J2/J3 coupling polygon (fitted by T7B 2026-06-01) provides the real protection — per-axis cap was the workaround for missing polygon.",
      "J1": "both ends intentionally pushed to limit during outer_left135/right135",
      "J2_upper": "from floor_0 (J2=82.8, pushed to limit)",
      "J2_lower": "spec fallback (observed min -14.7°, 10.3° from spec → not trusted)",
      "J3_upper": "spec — coupling polygon J3 - J2 ≤ 60° enforces the real mechanical envelope (see j2_j3_coupling). Per-axis spec is a sanity backstop only.",
      "J3_lower": "spec fallback (real arm not pushed to J3 lower limit)",
      "J4": "spec fallback — J4 was not exercised (random subset)"
    }
  },

  "j2_j3_coupling": [
    {"j2_coeff": -1.0, "j3_coeff": 1.0, "max_value": 59.95, "label": "j3_minus_j2_le_60"}
  ],

  "_coupling_note": {
    "status": "FITTED_BY_T7B",
    "fitted_at": "2026-06-01",
    "source": "outputs/limits_t7b_20260601.json (9 unique points from 5 J2 samples)",
    "constraint": "J3 - J2 ≤ 60°  ⇔  -1·J2 + 1·J3 ≤ 60  (max_value=59.95 = midpoint between known-reachable J3-J2=59 and controller-rejected J3-J2=60)",
    "fit_evidence": "4/4 alarm triggers fall exactly at J3-J2=60: (J2=0, alarm at J3=60), (J2=-5, alarm at J3=55), (J2=-10, alarm at J3=50), (J2=+5, alarm at J3=65). 5th sample at J2=+20 reached J3=77 (limited by per-axis cap 77.3°) without alarm — consistent with J3-J2=57 < 60.",
    "physical_meaning": "MG400 parallel four-bar linkage: when the relative angle between the upper arm (J2) and forearm (J3) exceeds 60°, the linkage hits a mechanical fold limit. Constraint is linear (not piecewise) — original SDK doc does not document this; discovered empirically.",
    "factory_pose_safe": "factory pose J3≈59.903 from PROGRESS finding 4 — 59.903 < 59.95, accepted by polygon. Phase 5 motion can resume from factory pose.",
    "v2_algorithm_note": "calibrate_bounds T7A was designed for noisy piecewise envelopes; T7B's data was too clean (4 alarm triggers exactly linear) so the polygon was hand-derived rather than fit. See PROGRESS finding 19."
  },

  "_future_tool_offset": {
    "note": "Phase 6 controller will add tool transforms. z_min is currently for bare flange.",
    "formula": "z_min_effective_for_tool = z_min_mm + tool.z_offset_mm",
    "example": "Gripper extending 50mm below flange: z_min_effective = -197.05 + 50 = -147.05mm"
  }
}
